tvtsplit/__about__.py
tvtsplit/__init__.py
tvtsplit/tvtsplit.py
tvtsplit-0.0.1.dist-info/METADATA
tvtsplit-0.0.1.dist-info/WHEEL
tvtsplit-0.0.1.dist-info/licenses/LICENSE.txt
tvtsplit-0.0.1.dist-info/RECORD
