Metadata-Version: 2.3
Name: tvtsplit
Version: 0.0.1
Project-URL: Documentation, https://github.com/anyumuenyumuboto/tvtsplit#readme
Project-URL: Issues, https://github.com/anyumuenyumuboto/tvtsplit/issues
Project-URL: Source, https://github.com/anyumuenyumuboto/tvtsplit
Author-email: Minato Hatakeyama <tianshanminato965@gmail.com>
License-Expression: MIT
License-File: LICENSE.txt
Classifier: Development Status :: 4 - Beta
Classifier: Programming Language :: Python
Classifier: Programming Language :: Python :: 3.8
Classifier: Programming Language :: Python :: 3.9
Classifier: Programming Language :: Python :: 3.10
Classifier: Programming Language :: Python :: 3.11
Classifier: Programming Language :: Python :: 3.12
Classifier: Programming Language :: Python :: Implementation :: CPython
Classifier: Programming Language :: Python :: Implementation :: PyPy
Requires-Python: >=3.8
Requires-Dist: polars
Provides-Extra: dev
Requires-Dist: hatch; extra == 'dev'
Requires-Dist: twine; extra == 'dev'
